streamlit_keplergl/__init__.py
streamlit_keplergl-0.3.0.dist-info/LICENSE
streamlit_keplergl-0.3.0.dist-info/METADATA
streamlit_keplergl-0.3.0.dist-info/WHEEL
streamlit_keplergl-0.3.0.dist-info/top_level.txt
streamlit_keplergl-0.3.0.dist-info/RECORD
