Metadata-Version: 2.1
Name: streamlit-keplergl
Version: 0.3.0
Summary: Streamlit Component for rendering kepler.gl maps
Home-page: https://github.com/chrieke/streamlit-keplergl
Author: Christoph Rieke
Author-email: 
License: MIT
Platform: UNKNOWN
Requires-Python: >=3.6
License-File: LICENSE
